{
  "date": "2026-10-05",
  "month": 10,
  "day": 5,
  "dayOfWeek": 1,
  "tone": 1,
  "fast": {
    "level": "ordinary",
    "label_en": "Week 19 after Pentecost",
    "label_uk": "19-й тиждень після П'ятидесятниці"
  },
  "fastCode": "19d",
  "rank": {
    "level": "ordinary",
    "label_en": "Ordinary",
    "label_uk": "Звичайний"
  },
  "rankCode": "-",
  "saints": {
    "uk": [
      "Тиждень 20-ий по Зісланні Святого Духа.",
      "Святої мучениці Харитини"
    ],
    "en": "St. Martyr Charitina"
  },
  "troparion": "",
  "kontakion": "",
  "rubrics": "Вечірня: катизми нема. На «Господи, взиваю» 6 стихир: 3 Октоїха, 3 мчц., Сл., І нині: богород. Прокімен дня. Стиховня Октоїха. По «Отче наш»: тропар мчц., Сл., І нині: богород. відпустовий за гласом тропаря мчц. і за днем тижня. Відпуст середній з помин. мчц.\nУтреня: по «Бог Господь»: тропар мчц. (2), Сл., І нині: богород. відпустовий за гласом тропаря мчц. Катизми черг., сідальні Октоїха. Пс. 50. Канон Октоїха і мчц. На 9-ій пісні – «Чеснішу від херувимів». По 9-ій – світильний Октоїха, Сл.: світильний мчц., І нині: його богород. Стиховня Октоїха. По «Отче наш»: тропар мчц., Сл., І нині: богород. за гласом тропаря мчц. і за днем тижня. Відпуст середній з помин. мчц.\nЧаси: на 1-му – дня; на 6-му – храму; на 3-му та 9-му – мчц.\nЛітургія: вся Служба – дня. Ап. – Флп. 241 зач.; 2, 12-16. Єв. – Лк. 25 зач.; 6, 24-30.",
  "services": {
    "vespers": false,
    "matins": false,
    "compline": false
  }
}